MANIFEST.in
README.rst
setup.py
dirsnap/__init__.py
dirsnap/archive.py
dirsnap/cli.py
dirsnap/gist.py
dirsnap.egg-info/PKG-INFO
dirsnap.egg-info/SOURCES.txt
dirsnap.egg-info/dependency_links.txt
dirsnap.egg-info/entry_points.txt
dirsnap.egg-info/requires.txt
dirsnap.egg-info/top_level.txt