Metadata-Version: 1.0
Name: dirsnap
Version: 0.0.3
Summary: Takes a snapshot of a directory, uploads to a public URL.
Home-page: https://github.com/kennethreitz/dirsnap
Author: Kenneth Reitz
Author-email: me@kennethreitz.com
License: BSD
Platform: UNKNOWN
Classifier: Intended Audience :: Developers
Classifier: Natural Language :: English
Classifier: License :: OSI Approved :: BSD License
Classifier: Programming Language :: Python
Classifier: Programming Language :: Python :: 2.6
Classifier: Programming Language :: Python :: 2.7
